quickquestion/__init__.py
quickquestion/llm_provider.py
quickquestion/qq.py
quickquestion/settings_manager.py
qq2-0.1.1.dist-info/LICENSE
qq2-0.1.1.dist-info/METADATA
qq2-0.1.1.dist-info/WHEEL
qq2-0.1.1.dist-info/entry_points.txt
qq2-0.1.1.dist-info/top_level.txt
qq2-0.1.1.dist-info/RECORD
