Metadata-Version: 2.1
Name: qq2
Version: 0.1.1
Summary: A CLI tool for getting quick command-line suggestions using any LLM potentially available
Home-page: https://southbrucke.com
Author: Cristian Vyhmeister
Author-email: cv@southbrucke.com
License: Proprietary
Classifier: Programming Language :: Python :: 3
Classifier: License :: Other/Proprietary License
Classifier: Operating System :: OS Independent
Classifier: Development Status :: 4 - Beta
Classifier: Environment :: Console
Classifier: Topic :: Utilities
Classifier: Topic :: System :: Shells
Classifier: Topic :: Terminals
Classifier: Intended Audience :: Developers
Classifier: Intended Audience :: System Administrators
Classifier: Intended Audience :: End Users/Desktop
Requires-Python: >=3.6
License-File: LICENSE
Requires-Dist: requests>=2.31.0
Requires-Dist: rich>=13.7.0
Requires-Dist: anthropic>=0.18.1
